{
  "formatVersion": 1,
  "database": {
    "version": 1,
    "identityHash": "b4ed8573af907902e312f78836724dd1",
    "entities": [
      {
        "tableName": "gunpla_items",
        "createSql": "CREATE TABLE IF NOT EXISTS `${TABLE_NAME}` (`id` TEXT NOT NULL, `name` TEXT NOT NULL, `grade` TEXT NOT NULL, `price` INTEGER, `imageData` BLOB, `url` TEXT, `releaseDate` INTEGER, `restockDate` INTEGER, `purchasedDate` INTEGER, `purchaseStoreId` TEXT, `priority` INTEGER NOT NULL, `tagColor` INTEGER NOT NULL, PRIMARY KEY(`id`))",
        "fields": [
          {
            "fieldPath": "id",
            "columnName": "id",
            "affinity": "TEXT",
            "notNull": true
          },
          {
            "fieldPath": "name",
            "columnName": "name",
            "affinity": "TEXT",
            "notNull": true
          },
          {
            "fieldPath": "grade",
            "columnName": "grade",
            "affinity": "TEXT",
            "notNull": true
          },
          {
            "fieldPath": "price",
            "columnName": "price",
            "affinity": "INTEGER",
            "notNull": false
          },
          {
            "fieldPath": "imageData",
            "columnName": "imageData",
            "affinity": "BLOB",
            "notNull": false
          },
          {
            "fieldPath": "url",
            "columnName": "url",
            "affinity": "TEXT",
            "notNull": false
          },
          {
            "fieldPath": "releaseDate",
            "columnName": "releaseDate",
            "affinity": "INTEGER",
            "notNull": false
          },
          {
            "fieldPath": "restockDate",
            "columnName": "restockDate",
            "affinity": "INTEGER",
            "notNull": false
          },
          {
            "fieldPath": "purchasedDate",
            "columnName": "purchasedDate",
            "affinity": "INTEGER",
            "notNull": false
          },
          {
            "fieldPath": "purchaseStoreId",
            "columnName": "purchaseStoreId",
            "affinity": "TEXT",
            "notNull": false
          },
          {
            "fieldPath": "priority",
            "columnName": "priority",
            "affinity": "INTEGER",
            "notNull": true
          },
          {
            "fieldPath": "tagColor",
            "columnName": "tagColor",
            "affinity": "INTEGER",
            "notNull": true
          }
        ],
        "primaryKey": {
          "autoGenerate": false,
          "columnNames": [
            "id"
          ]
        },
        "indices": [],
        "foreignKeys": []
      },
      {
        "tableName": "stores",
        "createSql": "CREATE TABLE IF NOT EXISTS `${TABLE_NAME}` (`id` TEXT NOT NULL, `name` TEXT NOT NULL, `latitude` REAL NOT NULL, `longitude` REAL NOT NULL, `isFavorite` INTEGER NOT NULL, `averageDelayHours` REAL NOT NULL, PRIMARY KEY(`id`))",
        "fields": [
          {
            "fieldPath": "id",
            "columnName": "id",
            "affinity": "TEXT",
            "notNull": true
          },
          {
            "fieldPath": "name",
            "columnName": "name",
            "affinity": "TEXT",
            "notNull": true
          },
          {
            "fieldPath": "latitude",
            "columnName": "latitude",
            "affinity": "REAL",
            "notNull": true
          },
          {
            "fieldPath": "longitude",
            "columnName": "longitude",
            "affinity": "REAL",
            "notNull": true
          },
          {
            "fieldPath": "isFavorite",
            "columnName": "isFavorite",
            "affinity": "INTEGER",
            "notNull": true
          },
          {
            "fieldPath": "averageDelayHours",
            "columnName": "averageDelayHours",
            "affinity": "REAL",
            "notNull": true
          }
        ],
        "primaryKey": {
          "autoGenerate": false,
          "columnNames": [
            "id"
          ]
        },
        "indices": [],
        "foreignKeys": []
      },
      {
        "tableName": "stock_delay_records",
        "createSql": "CREATE TABLE IF NOT EXISTS `${TABLE_NAME}` (`id` TEXT NOT NULL, `storeId` TEXT NOT NULL, `itemId` TEXT NOT NULL, `restockDate` INTEGER NOT NULL, `actualStockDate` INTEGER NOT NULL, `delayHours` REAL NOT NULL, PRIMARY KEY(`id`))",
        "fields": [
          {
            "fieldPath": "id",
            "columnName": "id",
            "affinity": "TEXT",
            "notNull": true
          },
          {
            "fieldPath": "storeId",
            "columnName": "storeId",
            "affinity": "TEXT",
            "notNull": true
          },
          {
            "fieldPath": "itemId",
            "columnName": "itemId",
            "affinity": "TEXT",
            "notNull": true
          },
          {
            "fieldPath": "restockDate",
            "columnName": "restockDate",
            "affinity": "INTEGER",
            "notNull": true
          },
          {
            "fieldPath": "actualStockDate",
            "columnName": "actualStockDate",
            "affinity": "INTEGER",
            "notNull": true
          },
          {
            "fieldPath": "delayHours",
            "columnName": "delayHours",
            "affinity": "REAL",
            "notNull": true
          }
        ],
        "primaryKey": {
          "autoGenerate": false,
          "columnNames": [
            "id"
          ]
        },
        "indices": [],
        "foreignKeys": []
      },
      {
        "tableName": "patrol_plans",
        "createSql": "CREATE TABLE IF NOT EXISTS `${TABLE_NAME}` (`id` TEXT NOT NULL, `date` INTEGER NOT NULL, `time` INTEGER NOT NULL, `storeId` TEXT NOT NULL, `targetItemIds` TEXT NOT NULL, `notifyEnabled` INTEGER NOT NULL, PRIMARY KEY(`id`))",
        "fields": [
          {
            "fieldPath": "id",
            "columnName": "id",
            "affinity": "TEXT",
            "notNull": true
          },
          {
            "fieldPath": "date",
            "columnName": "date",
            "affinity": "INTEGER",
            "notNull": true
          },
          {
            "fieldPath": "time",
            "columnName": "time",
            "affinity": "INTEGER",
            "notNull": true
          },
          {
            "fieldPath": "storeId",
            "columnName": "storeId",
            "affinity": "TEXT",
            "notNull": true
          },
          {
            "fieldPath": "targetItemIds",
            "columnName": "targetItemIds",
            "affinity": "TEXT",
            "notNull": true
          },
          {
            "fieldPath": "notifyEnabled",
            "columnName": "notifyEnabled",
            "affinity": "INTEGER",
            "notNull": true
          }
        ],
        "primaryKey": {
          "autoGenerate": false,
          "columnNames": [
            "id"
          ]
        },
        "indices": [],
        "foreignKeys": []
      }
    ],
    "views": [],
    "setupQueries": [
      "CREATE TABLE IF NOT EXISTS room_master_table (id INTEGER PRIMARY KEY,identity_hash TEXT)",
      "INSERT OR REPLACE INTO room_master_table (id,identity_hash) VALUES(42, 'b4ed8573af907902e312f78836724dd1')"
    ]
  }
}